str_mut_signatures/__init__.py
str_mut_signatures/cli.py
str_mut_signatures/extract_tally/extract_mutations.py
str_mut_signatures/extract_tally/filter.py
str_mut_signatures/extract_tally/tally.py
str_mut_signatures/extract_tally/validate.py
str_mut_signatures/nmf/__init__.py
str_mut_signatures/nmf/nmf.py
str_mut_signatures/nmf/plot.py
str_mut_signatures-2.0.0.dist-info/licenses/LICENSE
str_mut_signatures-2.0.0.dist-info/METADATA
str_mut_signatures-2.0.0.dist-info/WHEEL
str_mut_signatures-2.0.0.dist-info/entry_points.txt
str_mut_signatures-2.0.0.dist-info/top_level.txt
str_mut_signatures-2.0.0.dist-info/RECORD
