Metadata-Version: 2.4
Name: str_mut_signatures
Version: 2.0.0
Summary: Extract STR signatures from annotated VCF
Home-page: https://github.com/acg-team/str_mut_signatures
Author: Olesia Kondrateva
Author-email: Olesia Kondrateva <xkdnoa@gmail.com>
License: MIT
Project-URL: Homepage, https://github.com/acg-team/str_mut_signatures
Project-URL: Repository, https://github.com/acg-team/str_mut_signatures
Project-URL: Documentation, https://github.com/acg-team/str_mut_signatures/#readme
Project-URL: Bug Tracker, https://github.com/acg-team/str_mut_signatures/issues
Keywords: str,mutation,signature,bioinformatics,vcf
Classifier: Development Status :: 4 - Beta
Classifier: Intended Audience :: Developers
Classifier: Intended Audience :: Science/Research
Classifier: License :: OSI Approved :: MIT License
Classifier: Natural Language :: English
Classifier: Operating System :: OS Independent
Classifier: Programming Language :: Python :: 3
Classifier: Programming Language :: Python :: 3.8
Classifier: Programming Language :: Python :: 3.9
Classifier: Programming Language :: Python :: 3.10
Classifier: Programming Language :: Python :: 3.11
Classifier: Programming Language :: Python :: 3.12
Classifier: Programming Language :: Python :: 3.13
Classifier: Topic :: Scientific/Engineering :: Bio-Informatics
Requires-Python: >=3.8
License-File: LICENSE
Requires-Dist: pandas>=2.0
Requires-Dist: numpy>=1.24
Requires-Dist: scikit-learn>=1.3
Requires-Dist: scipy>=1.10
Requires-Dist: matplotlib>=3.7
Requires-Dist: trtools
Provides-Extra: dev
Requires-Dist: pytest>=8.0.0; extra == "dev"
Requires-Dist: pytest-cov>=4.1.0; extra == "dev"
Requires-Dist: ruff>=0.3.5; extra == "dev"
Requires-Dist: tox>=4.0.0; extra == "dev"
Requires-Dist: coverage>=7.0.0; extra == "dev"
Requires-Dist: twine>=4.0.0; extra == "dev"
Requires-Dist: bump2version>=1.0.1; extra == "dev"
Requires-Dist: watchdog>=3.0.0; extra == "dev"
Requires-Dist: sphinx; extra == "dev"
Requires-Dist: sphinx-rtd-theme; extra == "dev"
Requires-Dist: myst-parser; extra == "dev"
Requires-Dist: sphinx-argparse; extra == "dev"
Dynamic: author
Dynamic: home-page
Dynamic: license-file
Dynamic: requires-python
